bijou/__init__.py
bijou/datasets.py
bijou/hook.py
bijou/learner.py
bijou/metrics.py
bijou/modules.py
bijou/utils.py
bijou/callbacks/__init__.py
bijou/callbacks/basic_callbacks.py
bijou/callbacks/interpreters.py
bijou/callbacks/interpreters_dgl.py
bijou/callbacks/interpreters_pyg.py
bijou/callbacks/performance.py
bijou/callbacks/transforms.py
bijou/data/__init__.py
bijou/data/data.py
bijou/data/data_dgl.py
bijou/data/data_pyg.py
bijou-0.1.7.dist-info/LICENSE
bijou-0.1.7.dist-info/METADATA
bijou-0.1.7.dist-info/WHEEL
bijou-0.1.7.dist-info/top_level.txt
bijou-0.1.7.dist-info/RECORD
