Metadata-Version: 2.1
Name: bijou
Version: 0.1.7
Summary: A fastai-like framework for training, tuning and probing pytorch models, which is compatible with pytorch_geometric.
Home-page: https://github.com/hitlic/bijou
Author: hitlic
Author-email: liuchen.lic@gmail.com
License: MIT
Platform: UNKNOWN
Classifier: Development Status :: 3 - Alpha
Classifier: Programming Language :: Python :: 3
Classifier: Operating System :: OS Independent
Requires-Python: >=3.5
Requires-Dist: torch (>1.1)
Requires-Dist: tqdm (>4.40)
Requires-Dist: matplotlib (>3.1)
Requires-Dist: networkx (>=2.3)
Requires-Dist: requests (>2.20.0)
